pyreads/__init__.py
pyreads/_http.py
pyreads/_parser.py
pyreads/core.py
pyreads/models.py
pyreads-0.3.4.dist-info/licenses/LICENSE
pyreads-0.3.4.dist-info/METADATA
pyreads-0.3.4.dist-info/WHEEL
pyreads-0.3.4.dist-info/top_level.txt
pyreads-0.3.4.dist-info/RECORD
