Metadata-Version: 2.4
Name: pyreads
Version: 0.3.4
Summary: PyReads package to process Goodreads site data.
Author-email: Jeremy Kazimer <jeremykazimer@gmail.com>
License-Expression: Apache-2.0
Project-URL: source, https://github.com/jeremy-kazimer/PyReads
Keywords: goodreads,webscraper,books
Requires-Python: >=3.11
License-File: LICENSE
Requires-Dist: httpx==0.28.1
Requires-Dist: bs4==0.0.2
Requires-Dist: lxml==6.0.0
Requires-Dist: pandas==2.3.1
Requires-Dist: pydantic==2.11.7
Requires-Dist: tqdm==4.67.1
Dynamic: license-file
